Workbook

Sheet README
A1: Revenue Share, Reconciliation & Profitability Model — Work Sample
A2: ILLUSTRATIVE DATA ONLY — all processors, partners, merchants and figures are fictional.
A4: Purpose | B4: Demonstrates an end-to-end residual revenue workflow: normalized source data → merchant/partner mapping → revenue-share rules → partner payouts → company net revenue → bank reconciliation → profitability → forecast.
A5: Data flow | B5: Residual_Data → Merchant_Map + Partner_Rules → Rev_Share_Calc → Reconciliation → Profitability → Forecast
A7: Tab | B7: What it does
A8: Partner_Rules | B8: Default partner splits and split-of-split (sub-partner) rules.
A9: Merchant_Map | B9: Merchant/DBA → processor, gateway, partner; merchant-level split overrides; effective split.
A10: Residual_Data | B10: Normalized monthly source data (one row per merchant / source / revenue type / month). Partner payout and net revenue calculated per row.
A11: Rev_Share_Calc | B11: Selected-month payout calc by merchant, exception flags (missing residual, MoM swings), partner payout summary incl. paid vs. outstanding.
A12: Reconciliation | B12: Report-to-bank reconciliation by source with variance categorization, owner, status and an unexplained-variance check.
A13: Profitability | B13: TTM volume, gross revenue, residual yield, partner payout and net revenue by processor and partner; monthly trend.
A14: Forecast | B14: 12-month driver-based forecast (volume growth, attrition, yield, payout %) with Downside/Base/Upside selector.
A15: Portal_Audit | B15: Processor/gateway portal inventory: reporting capability, data access, and access governance (2FA, offboarding).
A17: Legend
A18: Blue text | B18: Hardcoded input / source data — edit these
A19: Black text | B19: Formula — do not edit
A20: Green text | B20: Link to another tab
A21: Yellow fill | B21: Key assumption or selector
A23: Key definitions
A24: Gross Revenue | B24: Processing residual + gateway fees, as reported by source. Processor residuals are reported net of processing expense — no further cost is deducted (avoids double-counting).
A25: Residual Yield | B25: Processing Residual ÷ Processing Volume, shown in basis points.
A26: Partner Payout | B26: Gross Revenue × Effective Split. Effective split = merchant override if present, else partner default.
A27: Split-of-split | B27: Sub-partner receives a % of the parent partner's payout; parent is paid net of it. Company cost is unchanged.
A28: Company Net Revenue | B28: Gross Revenue − total Partner Payout. Not true net profit: operating cost allocation is out of scope.

Sheet Partner_Rules
A1: Partner Revenue-Share Rules
A2: ILLUSTRATIVE DATA ONLY — all processors, partners, merchants and figures are fictional.
A4: Partner | B4: Default Split % | C4: Sub-Partner (Split-of-Split) | D4: Sub-Partner % of Partner Payout | E4: Notes
A5: House (Direct) | B5: 0 | D5: 0 | E5: No partner — company retains 100%
A6: Partner Alpha | B6: 0.4 | D6: 0 | E6: Standard referral agreement
A7: Partner Beta | B7: 0.35 | C7: Partner Gamma | D7: 0.25 | E7: Pays 25% of its share to Partner Gamma
A8: Partner Gamma | B8: 0 | D8: 0 | E8: Paid only via Beta split-of-split
A9: Partner Delta | B9: 0.5 | D9: 0 | E9: Agency agreement; merchant overrides possible

Sheet Merchant_Map
A1: Merchant / DBA Mapping
A2: ILLUSTRATIVE DATA ONLY — all processors, partners, merchants and figures are fictional.
A4: Merchant ID | B4: DBA | C4: Processor | D4: Gateway | E4: Partner | F4: Override Split % | G4: Effective Split % | H4: Sub-Partner %
A5: M-001 | B5: Merchant 001 (DBA) | C5: Processor A | D5: None | E5: Partner Alpha | G5: =IF(F5<>"",F5,INDEX(Partner_Rules!$B$5:$B$9,MATCH(E5,Partner_Rules!$A$5:$A$9,0))) -> 0.4 | H5: =INDEX(Partner_Rules!$D$5:$D$9,MATCH(E5,Partner_Rules!$A$5:$A$9,0)) -> 0
A6: M-002 | B6: Merchant 002 (DBA) | C6: Processor B | D6: Gateway G | E6: Partner Beta | G6: =IF(F6<>"",F6,INDEX(Partner_Rules!$B$5:$B$9,MATCH(E6,Partner_Rules!$A$5:$A$9,0))) -> 0.35 | H6: =INDEX(Partner_Rules!$D$5:$D$9,MATCH(E6,Partner_Rules!$A$5:$A$9,0)) -> 0.25
A7: M-003 | B7: Merchant 003 (DBA) | C7: Processor C | D7: None | E7: House (Direct) | G7: =IF(F7<>"",F7,INDEX(Partner_Rules!$B$5:$B$9,MATCH(E7,Partner_Rules!$A$5:$A$9,0))) -> 0 | H7: =INDEX(Partner_Rules!$D$5:$D$9,MATCH(E7,Partner_Rules!$A$5:$A$9,0)) -> 0
A8: M-004 | B8: Merchant 004 (DBA) | C8: Processor D | D8: Gateway G | E8: Partner Delta | G8: =IF(F8<>"",F8,INDEX(Partner_Rules!$B$5:$B$9,MATCH(E8,Partner_Rules!$A$5:$A$9,0))) -> 0.5 | H8: =INDEX(Partner_Rules!$D$5:$D$9,MATCH(E8,Partner_Rules!$A$5:$A$9,0)) -> 0
A9: M-005 | B9: Merchant 005 (DBA) | C9: Processor A | D9: None | E9: Partner Alpha | G9: =IF(F9<>"",F9,INDEX(Partner_Rules!$B$5:$B$9,MATCH(E9,Partner_Rules!$A$5:$A$9,0))) -> 0.4 | H9: =INDEX(Partner_Rules!$D$5:$D$9,MATCH(E9,Partner_Rules!$A$5:$A$9,0)) -> 0
A10: M-006 | B10: Merchant 006 (DBA) | C10: Processor B | D10: Gateway G | E10: Partner Alpha | G10: =IF(F10<>"",F10,INDEX(Partner_Rules!$B$5:$B$9,MATCH(E10,Partner_Rules!$A$5:$A$9,0))) -> 0.4 | H10: =INDEX(Partner_Rules!$D$5:$D$9,MATCH(E10,Partner_Rules!$A$5:$A$9,0)) -> 0
A11: M-007 | B11: Merchant 007 (DBA) | C11: Processor C | D11: None | E11: Partner Beta | F11: 0.45 | G11: =IF(F11<>"",F11,INDEX(Partner_Rules!$B$5:$B$9,MATCH(E11,Partner_Rules!$A$5:$A$9,0))) -> 0.45 | H11: =INDEX(Partner_Rules!$D$5:$D$9,MATCH(E11,Partner_Rules!$A$5:$A$9,0)) -> 0.25
A12: M-008 | B12: Merchant 008 (DBA) | C12: Processor D | D12: Gateway G | E12: House (Direct) | G12: =IF(F12<>"",F12,INDEX(Partner_Rules!$B$5:$B$9,MATCH(E12,Partner_Rules!$A$5:$A$9,0))) -> 0 | H12: =INDEX(Partner_Rules!$D$5:$D$9,MATCH(E12,Partner_Rules!$A$5:$A$9,0)) -> 0
A13: M-009 | B13: Merchant 009 (DBA) | C13: Processor A | D13: None | E13: Partner Delta | G13: =IF(F13<>"",F13,INDEX(Partner_Rules!$B$5:$B$9,MATCH(E13,Partner_Rules!$A$5:$A$9,0))) -> 0.5 | H13: =INDEX(Partner_Rules!$D$5:$D$9,MATCH(E13,Partner_Rules!$A$5:$A$9,0)) -> 0
A14: M-010 | B14: Merchant 010 (DBA) | C14: Processor B | D14: Gateway G | E14: Partner Alpha | G14: =IF(F14<>"",F14,INDEX(Partner_Rules!$B$5:$B$9,MATCH(E14,Partner_Rules!$A$5:$A$9,0))) -> 0.4 | H14: =INDEX(Partner_Rules!$D$5:$D$9,MATCH(E14,Partner_Rules!$A$5:$A$9,0)) -> 0
A15: M-011 | B15: Merchant 011 (DBA) | C15: Processor C | D15: None | E15: Partner Alpha | G15: =IF(F15<>"",F15,INDEX(Partner_Rules!$B$5:$B$9,MATCH(E15,Partner_Rules!$A$5:$A$9,0))) -> 0.4 | H15: =INDEX(Partner_Rules!$D$5:$D$9,MATCH(E15,Partner_Rules!$A$5:$A$9,0)) -> 0
A16: M-012 | B16: Merchant 012 (DBA) | C16: Processor D | D16: Gateway G | E16: Partner Beta | G16: =IF(F16<>"",F16,INDEX(Partner_Rules!$B$5:$B$9,MATCH(E16,Partner_Rules!$A$5:$A$9,0))) -> 0.35 | H16: =INDEX(Partner_Rules!$D$5:$D$9,MATCH(E16,Partner_Rules!$A$5:$A$9,0)) -> 0.25
A17: M-013 | B17: Merchant 013 (DBA) | C17: Processor A | D17: None | E17: House (Direct) | G17: =IF(F17<>"",F17,INDEX(Partner_Rules!$B$5:$B$9,MATCH(E17,Partner_Rules!$A$5:$A$9,0))) -> 0 | H17: =INDEX(Partner_Rules!$D$5:$D$9,MATCH(E17,Partner_Rules!$A$5:$A$9,0)) -> 0
A18: M-014 | B18: Merchant 014 (DBA) | C18: Processor B | D18: Gateway G | E18: Partner Delta | F18: 0.3 | G18: =IF(F18<>"",F18,INDEX(Partner_Rules!$B$5:$B$9,MATCH(E18,Partner_Rules!$A$5:$A$9,0))) -> 0.3 | H18: =INDEX(Partner_Rules!$D$5:$D$9,MATCH(E18,Partner_Rules!$A$5:$A$9,0)) -> 0
A19: M-015 | B19: Merchant 015 (DBA) | C19: Processor C | D19: None | E19: Partner Alpha | G19: =IF(F19<>"",F19,INDEX(Partner_Rules!$B$5:$B$9,MATCH(E19,Partner_Rules!$A$5:$A$9,0))) -> 0.4 | H19: =INDEX(Partner_Rules!$D$5:$D$9,MATCH(E19,Partner_Rules!$A$5:$A$9,0)) -> 0
A20: M-016 | B20: Merchant 016 (DBA) | C20: Processor D | D20: Gateway G | E20: Partner Alpha | G20: =IF(F20<>"",F20,INDEX(Partner_Rules!$B$5:$B$9,MATCH(E20,Partner_Rules!$A$5:$A$9,0))) -> 0.4 | H20: =INDEX(Partner_Rules!$D$5:$D$9,MATCH(E20,Partner_Rules!$A$5:$A$9,0)) -> 0
A21: M-017 | B21: Merchant 017 (DBA) | C21: Processor A | D21: None | E21: Partner Beta | G21: =IF(F21<>"",F21,INDEX(Partner_Rules!$B$5:$B$9,MATCH(E21,Partner_Rules!$A$5:$A$9,0))) -> 0.35 | H21: =INDEX(Partner_Rules!$D$5:$D$9,MATCH(E21,Partner_Rules!$A$5:$A$9,0)) -> 0.25
A22: M-018 | B22: Merchant 018 (DBA) | C22: Processor B | D22: Gateway G | E22: House (Direct) | G22: =IF(F22<>"",F22,INDEX(Partner_Rules!$B$5:$B$9,MATCH(E22,Partner_Rules!$A$5:$A$9,0))) -> 0 | H22: =INDEX(Partner_Rules!$D$5:$D$9,MATCH(E22,Partner_Rules!$A$5:$A$9,0)) -> 0
A23: M-019 | B23: Merchant 019 (DBA) | C23: Processor C | D23: None | E23: Partner Delta | G23: =IF(F23<>"",F23,INDEX(Partner_Rules!$B$5:$B$9,MATCH(E23,Partner_Rules!$A$5:$A$9,0))) -> 0.5 | H23: =INDEX(Partner_Rules!$D$5:$D$9,MATCH(E23,Partner_Rules!$A$5:$A$9,0)) -> 0
A24: M-020 | B24: Merchant 020 (DBA) | C24: Processor D | D24: Gateway G | E24: Partner Alpha | G24: =IF(F24<>"",F24,INDEX(Partner_Rules!$B$5:$B$9,MATCH(E24,Partner_Rules!$A$5:$A$9,0))) -> 0.4 | H24: =INDEX(Partner_Rules!$D$5:$D$9,MATCH(E24,Partner_Rules!$A$5:$A$9,0)) -> 0

Sheet Residual_Data
A1: Normalized Residual Source Data
A2: ILLUSTRATIVE DATA ONLY — all processors, partners, merchants and figures are fictional. Month stored as text (YYYY-MM).
A4: Month | B4: Merchant ID | C4: Source | D4: Revenue Type | E4: Volume ($) | F4: Gross Revenue ($) | G4: Partner | H4: Effective Split % | I4: Partner Payout ($) | J4: Company Net ($)
A5: 2025-10 | B5: M-001 | C5: Processor A | D5: Processing Residual | E5: 388061 | F5: 853.73 | G5: =INDEX(Merchant_Map!$E$5:$E$24,MATCH(B5,Merchant_Map!$A$5:$A$24,0)) -> Partner Alpha | H5: =INDEX(Merchant_Map!$G$5:$G$24,MATCH(B5,Merchant_Map!$A$5:$A$24,0)) -> 0.4 | I5: =F5*H5 -> 341.492 | J5: =F5-I5 -> 512.238
A6: 2025-11 | B6: M-001 | C6: Processor A | D6: Processing Residual | E6: 392914 | F6: 864.41 | G6: =INDEX(Merchant_Map!$E$5:$E$24,MATCH(B6,Merchant_Map!$A$5:$A$24,0)) -> Partner Alpha | H6: =INDEX(Merchant_Map!$G$5:$G$24,MATCH(B6,Merchant_Map!$A$5:$A$24,0)) -> 0.4 | I6: =F6*H6 -> 345.764 | J6: =F6-I6 -> 518.646
A7: 2025-12 | B7: M-001 | C7: Processor A | D7: Processing Residual | E7: 435275 | F7: 957.61 | G7: =INDEX(Merchant_Map!$E$5:$E$24,MATCH(B7,Merchant_Map!$A$5:$A$24,0)) -> Partner Alpha | H7: =INDEX(Merchant_Map!$G$5:$G$24,MATCH(B7,Merchant_Map!$A$5:$A$24,0)) -> 0.4 | I7: =F7*H7 -> 383.044 | J7: =F7-I7 -> 574.566
A8: 2026-01 | B8: M-001 | C8: Processor A | D8: Processing Residual | E8: 428128 | F8: 941.88 | G8: =INDEX(Merchant_Map!$E$5:$E$24,MATCH(B8,Merchant_Map!$A$5:$A$24,0)) -> Partner Alpha | H8: =INDEX(Merchant_Map!$G$5:$G$24,MATCH(B8,Merchant_Map!$A$5:$A$24,0)) -> 0.4 | I8: =F8*H8 -> 376.752 | J8: =F8-I8 -> 565.128
A9: 2026-02 | B9: M-001 | C9: Processor A | D9: Processing Residual | E9: 443711 | F9: 976.16 | G9: =INDEX(Merchant_Map!$E$5:$E$24,MATCH(B9,Merchant_Map!$A$5:$A$24,0)) -> Partner Alpha | H9: =INDEX(Merchant_Map!$G$5:$G$24,MATCH(B9,Merchant_Map!$A$5:$A$24,0)) -> 0.4 | I9: =F9*H9 -> 390.464 | J9: =F9-I9 -> 585.696
A10: 2026-03 | B10: M-001 | C10: Processor A | D10: Processing Residual | E10: 445014 | F10: 979.03 | G10: =INDEX(Merchant_Map!$E$5:$E$24,MATCH(B10,Merchant_Map!$A$5:$A$24,0)) -> Partner Alpha | H10: =INDEX(Merchant_Map!$G$5:$G$24,MATCH(B10,Merchant_Map!$A$5:$A$24,0)) -> 0.4 | I10: =F10*H10 -> 391.612 | J10: =F10-I10 -> 587.418
A11: 2026-04 | B11: M-001 | C11: Processor A | D11: Processing Residual | E11: 440177 | F11: 968.39 | G11: =INDEX(Merchant_Map!$E$5:$E$24,MATCH(B11,Merchant_Map!$A$5:$A$24,0)) -> Partner Alpha | H11: =INDEX(Merchant_Map!$G$5:$G$24,MATCH(B11,Merchant_Map!$A$5:$A$24,0)) -> 0.4 | I11: =F11*H11 -> 387.356 | J11: =F11-I11 -> 581.034
A12: 2026-05 | B12: M-001 | C12: Processor A | D12: Processing Residual | E12: 468712 | F12: 1031.17 | G12: =INDEX(Merchant_Map!$E$5:$E$24,MATCH(B12,Merchant_Map!$A$5:$A$24,0)) -> Partner Alpha | H12: =INDEX(Merchant_Map!$G$5:$G$24,MATCH(B12,Merchant_Map!$A$5:$A$24,0)) -> 0.4 | I12: =F12*H12 -> 412.468 | J12: =F12-I12 -> 618.702
A13: 2026-06 | B13: M-001 | C13: Processor A | D13: Processing Residual | E13: 442311 | F13: 973.08 | G13: =INDEX(Merchant_Map!$E$5:$E$24,MATCH(B13,Merchant_Map!$A$5:$A$24,0)) -> Partner Alpha | H13: =INDEX(Merchant_Map!$G$5:$G$24,MATCH(B13,Merchant_Map!$A$5:$A$24,0)) -> 0.4 | I13: =F13*H13 -> 389.232 | J13: =F13-I13 -> 583.848
A14: 2026-07 | B14: M-001 | C14: Processor A | D14: Processing Residual | E14: 457076 | F14: 1005.57 | G14: =INDEX(Merchant_Map!$E$5:$E$24,MATCH(B14,Merchant_Map!$A$5:$A$24,0)) -> Partner Alpha | H14: =INDEX(Merchant_Map!$G$5:$G$24,MATCH(B14,Merchant_Map!$A$5:$A$24,0)) -> 0.4 | I14: =F14*H14 -> 402.228 | J14: =F14-I14 -> 603.342
A15: 2026-08 | B15: M-001 | C15: Processor A | D15: Processing Residual | E15: 477861 | F15: 1051.29 | G15: =INDEX(Merchant_Map!$E$5:$E$24,MATCH(B15,Merchant_Map!$A$5:$A$24,0)) -> Partner Alpha | H15: =INDEX(Merchant_Map!$G$5:$G$24,MATCH(B15,Merchant_Map!$A$5:$A$24,0)) -> 0.4 | I15: =F15*H15 -> 420.516 | J15: =F15-I15 -> 630.774
A16: 2026-09 | B16: M-001 | C16: Processor A | D16: Processing Residual | E16: 471823 | F16: 1038.01 | G16: =INDEX(Merchant_Map!$E$5:$E$24,MATCH(B16,Merchant_Map!$A$5:$A$24,0)) -> Partner Alpha | H16: =INDEX(Merchant_Map!$G$5:$G$24,MATCH(B16,Merchant_Map!$A$5:$A$24,0)) -> 0.4 | I16: =F16*H16 -> 415.204 | J16: =F16-I16 -> 622.806
... A346: 2026-09 | B346: M-020 | C346: Gateway G | D346: Gateway Fee | E346: 0 | F346: 578 | G346: =INDEX(Merchant_Map!$E$5:$E$24,MATCH(B346,Merchant_Map!$A$5:$A$24,0)) -> Partner Alpha | H346: =INDEX(Merchant_Map!$G$5:$G$24,MATCH(B346,Merchant_Map!$A$5:$A$24,0)) -> 0.4 | I346: =F346*H346 -> 231.2 | J346: =F346-I346 -> 346.8

Sheet Rev_Share_Calc
A1: Monthly Revenue Share & Partner Payout Calculation
A2: ILLUSTRATIVE DATA ONLY — all processors, partners, merchants and figures are fictional.
A3: Selected Month | B3: 2026-09 | D3: Change the selected/prior month (YYYY-MM) to recalculate the entire sheet.
A4: Prior Month | B4: 2026-08
A7: Merchant ID | B7: DBA | C7: Processor | D7: Partner | E7: Volume ($) | F7: Processing Residual ($) | G7: Gateway Fee ($) | H7: Total Gross Revenue ($) | I7: Effective Split % | J7: Partner Payout ($) | K7: of which Sub-Partner ($) | L7: Company Net Revenue ($) | M7: Prior Month Gross ($) | N7: MoM Change % | O7: Exception Flag
A8: =Merchant_Map!A5 -> M-001 | B8: =Merchant_Map!B5 -> Merchant 001 (DBA) | C8: =Merchant_Map!C5 -> Processor A | D8: =Merchant_Map!E5 -> Partner Alpha | E8: =SUMIFS(Residual_Data!$E$5:$E$346,Residual_Data!$A$5:$A$346,$B$3,Residual_Data!$B$5:$B$346,A8) -> 471823 | F8: =SUMIFS(Residual_Data!$F$5:$F$346,Residual_Data!$A$5:$A$346,$B$3,Residual_Data!$B$5:$B$346,A8,Residual_Data!$D$5:$D$346,"Processing Residual") -> 1038.01 | G8: =SUMIFS(Residual_Data!$F$5:$F$346,Residual_Data!$A$5:$A$346,$B$3,Residual_Data!$B$5:$B$346,A8,Residual_Data!$D$5:$D$346,"Gateway Fee") -> 0 | H8: =F8+G8 -> 1038.01 | I8: =Merchant_Map!G5 -> 0.4 | J8: =H8*I8 -> 415.204 | K8: =J8*Merchant_Map!H5 -> 0 | L8: =H8-J8 -> 622.806 | M8: =SUMIFS(Residual_Data!$F$5:$F$346,Residual_Data!$A$5:$A$346,$B$4,Residual_Data!$B$5:$B$346,A8) -> 1051.29 | N8: =IF(M8=0,"",H8/M8-1) -> -0.0126321 | O8: =IF(AND(E8>0,F8=0),"VOLUME, NO RESIDUAL",IF(AND(M8>0,H8=0),"ZERO REVENUE",IF(AND(M8>0,ABS(N8)>0.25),"MoM >25%","")))
A9: =Merchant_Map!A6 -> M-002 | B9: =Merchant_Map!B6 -> Merchant 002 (DBA) | C9: =Merchant_Map!C6 -> Processor B | D9: =Merchant_Map!E6 -> Partner Beta | E9: =SUMIFS(Residual_Data!$E$5:$E$346,Residual_Data!$A$5:$A$346,$B$3,Residual_Data!$B$5:$B$346,A9) -> 833436 | F9: =SUMIFS(Residual_Data!$F$5:$F$346,Residual_Data!$A$5:$A$346,$B$3,Residual_Data!$B$5:$B$346,A9,Residual_Data!$D$5:$D$346,"Processing Residual") -> 2333.62 | G9: =SUMIFS(Residual_Data!$F$5:$F$346,Residual_Data!$A$5:$A$346,$B$3,Residual_Data!$B$5:$B$346,A9,Residual_Data!$D$5:$D$346,"Gateway Fee") -> 515.25 | H9: =F9+G9 -> 2848.87 | I9: =Merchant_Map!G6 -> 0.35 | J9: =H9*I9 -> 997.1045 | K9: =J9*Merchant_Map!H6 -> 249.27613 | L9: =H9-J9 -> 1851.7655 | M9: =SUMIFS(Residual_Data!$F$5:$F$346,Residual_Data!$A$5:$A$346,$B$4,Residual_Data!$B$5:$B$346,A9) -> 2907.58 | N9: =IF(M9=0,"",H9/M9-1) -> -0.02019205 | O9: =IF(AND(E9>0,F9=0),"VOLUME, NO RESIDUAL",IF(AND(M9>0,H9=0),"ZERO REVENUE",IF(AND(M9>0,ABS(N9)>0.25),"MoM >25%","")))
A10: =Merchant_Map!A7 -> M-003 | B10: =Merchant_Map!B7 -> Merchant 003 (DBA) | C10: =Merchant_Map!C7 -> Processor C | D10: =Merchant_Map!E7 -> House (Direct) | E10: =SUMIFS(Residual_Data!$E$5:$E$346,Residual_Data!$A$5:$A$346,$B$3,Residual_Data!$B$5:$B$346,A10) -> 738517 | F10: =SUMIFS(Residual_Data!$F$5:$F$346,Residual_Data!$A$5:$A$346,$B$3,Residual_Data!$B$5:$B$346,A10,Residual_Data!$D$5:$D$346,"Processing Residual") -> 2067.85 | G10: =SUMIFS(Residual_Data!$F$5:$F$346,Residual_Data!$A$5:$A$346,$B$3,Residual_Data!$B$5:$B$346,A10,Residual_Data!$D$5:$D$346,"Gateway Fee") -> 0 | H10: =F10+G10 -> 2067.85 | I10: =Merchant_Map!G7 -> 0 | J10: =H10*I10 -> 0 | K10: =J10*Merchant_Map!H7 -> 0 | L10: =H10-J10 -> 2067.85 | M10: =SUMIFS(Residual_Data!$F$5:$F$346,Residual_Data!$A$5:$A$346,$B$4,Residual_Data!$B$5:$B$346,A10) -> 2127.62 | N10: =IF(M10=0,"",H10/M10-1) -> -0.028092423 | O10: =IF(AND(E10>0,F10=0),"VOLUME, NO RESIDUAL",IF(AND(M10>0,H10=0),"ZERO REVENUE",IF(AND(M10>0,ABS(N10)>0.25),"MoM >25%","")))
A11: =Merchant_Map!A8 -> M-004 | B11: =Merchant_Map!B8 -> Merchant 004 (DBA) | C11: =Merchant_Map!C8 -> Processor D | D11: =Merchant_Map!E8 -> Partner Delta | E11: =SUMIFS(Residual_Data!$E$5:$E$346,Residual_Data!$A$5:$A$346,$B$3,Residual_Data!$B$5:$B$346,A11) -> 433679 | F11: =SUMIFS(Residual_Data!$F$5:$F$346,Residual_Data!$A$5:$A$346,$B$3,Residual_Data!$B$5:$B$346,A11,Residual_Data!$D$5:$D$346,"Processing Residual") -> 2081.66 | G11: =SUMIFS(Residual_Data!$F$5:$F$346,Residual_Data!$A$5:$A$346,$B$3,Residual_Data!$B$5:$B$346,A11,Residual_Data!$D$5:$D$346,"Gateway Fee") -> 280.1 | H11: =F11+G11 -> 2361.76 | I11: =Merchant_Map!G8 -> 0.5 | J11: =H11*I11 -> 1180.88 | K11: =J11*Merchant_Map!H8 -> 0 | L11: =H11-J11 -> 1180.88 | M11: =SUMIFS(Residual_Data!$F$5:$F$346,Residual_Data!$A$5:$A$346,$B$4,Residual_Data!$B$5:$B$346,A11) -> 2493.22 | N11: =IF(M11=0,"",H11/M11-1) -> -0.052726996 | O11: =IF(AND(E11>0,F11=0),"VOLUME, NO RESIDUAL",IF(AND(M11>0,H11=0),"ZERO REVENUE",IF(AND(M11>0,ABS(N11)>0.25),"MoM >25%","")))
A12: =Merchant_Map!A9 -> M-005 | B12: =Merchant_Map!B9 -> Merchant 005 (DBA) | C12: =Merchant_Map!C9 -> Processor A | D12: =Merchant_Map!E9 -> Partner Alpha | E12: =SUMIFS(Residual_Data!$E$5:$E$346,Residual_Data!$A$5:$A$346,$B$3,Residual_Data!$B$5:$B$346,A12) -> 0 | F12: =SUMIFS(Residual_Data!$F$5:$F$346,Residual_Data!$A$5:$A$346,$B$3,Residual_Data!$B$5:$B$346,A12,Residual_Data!$D$5:$D$346,"Processing Residual") -> 0 | G12: =SUMIFS(Residual_Data!$F$5:$F$346,Residual_Data!$A$5:$A$346,$B$3,Residual_Data!$B$5:$B$346,A12,Residual_Data!$D$5:$D$346,"Gateway Fee") -> 0 | H12: =F12+G12 -> 0 | I12: =Merchant_Map!G9 -> 0.4 | J12: =H12*I12 -> 0 | K12: =J12*Merchant_Map!H9 -> 0 | L12: =H12-J12 -> 0 | M12: =SUMIFS(Residual_Data!$F$5:$F$346,Residual_Data!$A$5:$A$346,$B$4,Residual_Data!$B$5:$B$346,A12) -> 3173.64 | N12: =IF(M12=0,"",H12/M12-1) -> -1 | O12: =IF(AND(E12>0,F12=0),"VOLUME, NO RESIDUAL",IF(AND(M12>0,H12=0),"ZERO REVENUE",IF(AND(M12>0,ABS(N12)>0.25),"MoM >25%",""))) -> ZERO REVENUE
A13: =Merchant_Map!A10 -> M-006 | B13: =Merchant_Map!B10 -> Merchant 006 (DBA) | C13: =Merchant_Map!C10 -> Processor B | D13: =Merchant_Map!E10 -> Partner Alpha | E13: =SUMIFS(Residual_Data!$E$5:$E$346,Residual_Data!$A$5:$A$346,$B$3,Residual_Data!$B$5:$B$346,A13) -> 1589288 | F13: =SUMIFS(Residual_Data!$F$5:$F$346,Residual_Data!$A$5:$A$346,$B$3,Residual_Data!$B$5:$B$346,A13,Residual_Data!$D$5:$D$346,"Processing Residual") -> 5721.44 | G13: =SUMIFS(Residual_Data!$F$5:$F$346,Residual_Data!$A$5:$A$346,$B$3,Residual_Data!$B$5:$B$346,A13,Residual_Data!$D$5:$D$346,"Gateway Fee") -> 959.9 | H13: =F13+G13 -> 6681.34 | I13: =Merchant_Map!G10 -> 0.4 | J13: =H13*I13 -> 2672.536 | K13: =J13*Merchant_Map!H10 -> 0 | L13: =H13-J13 -> 4008.804 | M13: =SUMIFS(Residual_Data!$F$5:$F$346,Residual_Data!$A$5:$A$346,$B$4,Residual_Data!$B$5:$B$346,A13) -> 6969.72 | N13: =IF(M13=0,"",H13/M13-1) -> -0.041376124 | O13: =IF(AND(E13>0,F13=0),"VOLUME, NO RESIDUAL",IF(AND(M13>0,H13=0),"ZERO REVENUE",IF(AND(M13>0,ABS(N13)>0.25),"MoM >25%","")))
A14: =Merchant_Map!A11 -> M-007 | B14: =Merchant_Map!B11 -> Merchant 007 (DBA) | C14: =Merchant_Map!C11 -> Processor C | D14: =Merchant_Map!E11 -> Partner Beta | E14: =SUMIFS(Residual_Data!$E$5:$E$346,Residual_Data!$A$5:$A$346,$B$3,Residual_Data!$B$5:$B$346,A14) -> 294565 | F14: =SUMIFS(Residual_Data!$F$5:$F$346,Residual_Data!$A$5:$A$346,$B$3,Residual_Data!$B$5:$B$346,A14,Residual_Data!$D$5:$D$346,"Processing Residual") -> 648.04 | G14: =SUMIFS(Residual_Data!$F$5:$F$346,Residual_Data!$A$5:$A$346,$B$3,Residual_Data!$B$5:$B$346,A14,Residual_Data!$D$5:$D$346,"Gateway Fee") -> 0 | H14: =F14+G14 -> 648.04 | I14: =Merchant_Map!G11 -> 0.45 | J14: =H14*I14 -> 291.618 | K14: =J14*Merchant_Map!H11 -> 72.9045 | L14: =H14-J14 -> 356.422 | M14: =SUMIFS(Residual_Data!$F$5:$F$346,Residual_Data!$A$5:$A$346,$B$4,Residual_Data!$B$5:$B$346,A14) -> 603.92 | N14: =IF(M14=0,"",H14/M14-1) -> 0.073056034 | O14: =IF(AND(E14>0,F14=0),"VOLUME, NO RESIDUAL",IF(AND(M14>0,H14=0),"ZERO REVENUE",IF(AND(M14>0,ABS(N14)>0.25),"MoM >25%","")))
A15: =Merchant_Map!A12 -> M-008 | B15: =Merchant_Map!B12 -> Merchant 008 (DBA) | C15: =Merchant_Map!C12 -> Processor D | D15: =Merchant_Map!E12 -> House (Direct) | E15: =SUMIFS(Residual_Data!$E$5:$E$346,Residual_Data!$A$5:$A$346,$B$3,Residual_Data!$B$5:$B$346,A15) -> 425018 | F15: =SUMIFS(Residual_Data!$F$5:$F$346,Residual_Data!$A$5:$A$346,$B$3,Residual_Data!$B$5:$B$346,A15,Residual_Data!$D$5:$D$346,"Processing Residual") -> 1190.05 | G15: =SUMIFS(Residual_Data!$F$5:$F$346,Residual_Data!$A$5:$A$346,$B$3,Residual_Data!$B$5:$B$346,A15,Residual_Data!$D$5:$D$346,"Gateway Fee") -> 275 | H15: =F15+G15 -> 1465.05 | I15: =Merchant_Map!G12 -> 0 | J15: =H15*I15 -> 0 | K15: =J15*Merchant_Map!H12 -> 0 | L15: =H15-J15 -> 1465.05 | M15: =SUMIFS(Residual_Data!$F$5:$F$346,Residual_Data!$A$5:$A$346,$B$4,Residual_Data!$B$5:$B$346,A15) -> 1485.93 | N15: =IF(M15=0,"",H15/M15-1) -> -0.014051806 | O15: =IF(AND(E15>0,F15=0),"VOLUME, NO RESIDUAL",IF(AND(M15>0,H15=0),"ZERO REVENUE",IF(AND(M15>0,ABS(N15)>0.25),"MoM >25%","")))
A16: =Merchant_Map!A13 -> M-009 | B16: =Merchant_Map!B13 -> Merchant 009 (DBA) | C16: =Merchant_Map!C13 -> Processor A | D16: =Merchant_Map!E13 -> Partner Delta | E16: =SUMIFS(Residual_Data!$E$5:$E$346,Residual_Data!$A$5:$A$346,$B$3,Residual_Data!$B$5:$B$346,A16) -> 788096 | F16: =SUMIFS(Residual_Data!$F$5:$F$346,Residual_Data!$A$5:$A$346,$B$3,Residual_Data!$B$5:$B$346,A16,Residual_Data!$D$5:$D$346,"Processing Residual") -> 3231.19 | G16: =SUMIFS(Residual_Data!$F$5:$F$346,Residual_Data!$A$5:$A$346,$B$3,Residual_Data!$B$5:$B$346,A16,Residual_Data!$D$5:$D$346,"Gateway Fee") -> 0 | H16: =F16+G16 -> 3231.19 | I16: =Merchant_Map!G13 -> 0.5 | J16: =H16*I16 -> 1615.595 | K16: =J16*Merchant_Map!H13 -> 0 | L16: =H16-J16 -> 1615.595 | M16: =SUMIFS(Residual_Data!$F$5:$F$346,Residual_Data!$A$5:$A$346,$B$4,Residual_Data!$B$5:$B$346,A16) -> 3167.81 | N16: =IF(M16=0,"",H16/M16-1) -> 0.020007513 | O16: =IF(AND(E16>0,F16=0),"VOLUME, NO RESIDUAL",IF(AND(M16>0,H16=0),"ZERO REVENUE",IF(AND(M16>0,ABS(N16)>0.25),"MoM >25%","")))
A17: =Merchant_Map!A14 -> M-010 | B17: =Merchant_Map!B14 -> Merchant 010 (DBA) | C17: =Merchant_Map!C14 -> Processor B | D17: =Merchant_Map!E14 -> Partner Alpha | E17: =SUMIFS(Residual_Data!$E$5:$E$346,Residual_Data!$A$5:$A$346,$B$3,Residual_Data!$B$5:$B$346,A17) -> 257582 | F17: =SUMIFS(Residual_Data!$F$5:$F$346,Residual_Data!$A$5:$A$346,$B$3,Residual_Data!$B$5:$B$346,A17,Residual_Data!$D$5:$D$346,"Processing Residual") -> 1056.09 | G17: =SUMIFS(Residual_Data!$F$5:$F$346,Residual_Data!$A$5:$A$346,$B$3,Residual_Data!$B$5:$B$346,A17,Residual_Data!$D$5:$D$346,"Gateway Fee") -> 176.5 | H17: =F17+G17 -> 1232.59 | I17: =Merchant_Map!G14 -> 0.4 | J17: =H17*I17 -> 493.036 | K17: =J17*Merchant_Map!H14 -> 0 | L17: =H17-J17 -> 739.554 | M17: =SUMIFS(Residual_Data!$F$5:$F$346,Residual_Data!$A$5:$A$346,$B$4,Residual_Data!$B$5:$B$346,A17) -> 1249.63 | N17: =IF(M17=0,"",H17/M17-1) -> -0.013636036 | O17: =IF(AND(E17>0,F17=0),"VOLUME, NO RESIDUAL",IF(AND(M17>0,H17=0),"ZERO REVENUE",IF(AND(M17>0,ABS(N17)>0.25),"MoM >25%","")))
A18: =Merchant_Map!A15 -> M-011 | B18: =Merchant_Map!B15 -> Merchant 011 (DBA) | C18: =Merchant_Map!C15 -> Processor C | D18: =Merchant_Map!E15 -> Partner Alpha | E18: =SUMIFS(Residual_Data!$E$5:$E$346,Residual_Data!$A$5:$A$346,$B$3,Residual_Data!$B$5:$B$346,A18) -> 676397 | F18: =SUMIFS(Residual_Data!$F$5:$F$346,Residual_Data!$A$5:$A$346,$B$3,Residual_Data!$B$5:$B$346,A18,Residual_Data!$D$5:$D$346,"Processing Residual") -> 3246.71 | G18: =SUMIFS(Residual_Data!$F$5:$F$346,Residual_Data!$A$5:$A$346,$B$3,Residual_Data!$B$5:$B$346,A18,Residual_Data!$D$5:$D$346,"Gateway Fee") -> 0 | H18: =F18+G18 -> 3246.71 | I18: =Merchant_Map!G15 -> 0.4 | J18: =H18*I18 -> 1298.684 | K18: =J18*Merchant_Map!H15 -> 0 | L18: =H18-J18 -> 1948.026 | M18: =SUMIFS(Residual_Data!$F$5:$F$346,Residual_Data!$A$5:$A$346,$B$4,Residual_Data!$B$5:$B$346,A18) -> 3112.89 | N18: =IF(M18=0,"",H18/M18-1) -> 0.042988991 | O18: =IF(AND(E18>0,F18=0),"VOLUME, NO RESIDUAL",IF(AND(M18>0,H18=0),"ZERO REVENUE",IF(AND(M18>0,ABS(N18)>0.25),"MoM >25%","")))
A19: =Merchant_Map!A16 -> M-012 | B19: =Merchant_Map!B16 -> Merchant 012 (DBA) | C19: =Merchant_Map!C16 -> Processor D | D19: =Merchant_Map!E16 -> Partner Beta | E19: =SUMIFS(Residual_Data!$E$5:$E$346,Residual_Data!$A$5:$A$346,$B$3,Residual_Data!$B$5:$B$346,A19) -> 2851200 | F19: =SUMIFS(Residual_Data!$F$5:$F$346,Residual_Data!$A$5:$A$346,$B$3,Residual_Data!$B$5:$B$346,A19,Residual_Data!$D$5:$D$346,"Processing Residual") -> 10264.32 | G19: =SUMIFS(Residual_Data!$F$5:$F$346,Residual_Data!$A$5:$A$346,$B$3,Residual_Data!$B$5:$B$346,A19,Residual_Data!$D$5:$D$346,"Gateway Fee") -> 1702.2 | H19: =F19+G19 -> 11966.52 | I19: =Merchant_Map!G16 -> 0.35 | J19: =H19*I19 -> 4188.282 | K19: =J19*Merchant_Map!H16 -> 1047.0705 | L19: =H19-J19 -> 7778.238 | M19: =SUMIFS(Residual_Data!$F$5:$F$346,Residual_Data!$A$5:$A$346,$B$4,Residual_Data!$B$5:$B$346,A19) -> 8384.02 | N19: =IF(M19=0,"",H19/M19-1) -> 0.42730098 | O19: =IF(AND(E19>0,F19=0),"VOLUME, NO RESIDUAL",IF(AND(M19>0,H19=0),"ZERO REVENUE",IF(AND(M19>0,ABS(N19)>0.25),"MoM >25%",""))) -> MoM >25%
... A27: =Merchant_Map!A24 -> M-020 | B27: =Merchant_Map!B24 -> Merchant 020 (DBA) | C27: =Merchant_Map!C24 -> Processor D | D27: =Merchant_Map!E24 -> Partner Alpha | E27: =SUMIFS(Residual_Data!$E$5:$E$346,Residual_Data!$A$5:$A$346,$B$3,Residual_Data!$B$5:$B$346,A27) -> 940104 | F27: =SUMIFS(Residual_Data!$F$5:$F$346,Residual_Data!$A$5:$A$346,$B$3,Residual_Data!$B$5:$B$346,A27,Residual_Data!$D$5:$D$346,"Processing Residual") -> 2068.23 | G27: =SUMIFS(Residual_Data!$F$5:$F$346,Residual_Data!$A$5:$A$346,$B$3,Residual_Data!$B$5:$B$346,A27,Residual_Data!$D$5:$D$346,"Gateway Fee") -> 578 | H27: =F27+G27 -> 2646.23 | I27: =Merchant_Map!G24 -> 0.4 | J27: =H27*I27 -> 1058.492 | K27: =J27*Merchant_Map!H24 -> 0 | L27: =H27-J27 -> 1587.738 | M27: =SUMIFS(Residual_Data!$F$5:$F$346,Residual_Data!$A$5:$A$346,$B$4,Residual_Data!$B$5:$B$346,A27) -> 2917.44 | N27: =IF(M27=0,"",H27/M27-1) -> -0.092961638 | O27: =IF(AND(E27>0,F27=0),"VOLUME, NO RESIDUAL",IF(AND(M27>0,H27=0),"ZERO REVENUE",IF(AND(M27>0,ABS(N27)>0.25),"MoM >25%","")))
A28: TOTAL | E28: =SUM(E8:E27) -> 16172784 | F28: =SUM(F8:F27) -> 54251.02 | G28: =SUM(G8:G27) -> 6323.25 | H28: =SUM(H8:H27) -> 60574.27 | I28: =IF(H28=0,0,J28/H28) -> 0.34669947 | J28: =SUM(J8:J27) -> 21001.068 | K28: =SUM(K8:K27) -> 1721.6416 | L28: =SUM(L8:L27) -> 39573.202 | M28: =SUM(M8:M27) -> 62558.23 | N28: =IF(M28=0,"",H28/M28-1) -> -0.031713813 | O28: =COUNTIF(O8:O27,"?*")&" exceptions" -> 3 exceptions
A30: Partner Payout Summary — Selected Month
A31: Partner | B31: Gross Revenue Attributed ($) | C31: Payout Earned ($) | D31: Effective Share % | E31: Amount Paid ($) | F31: Outstanding ($) | G31: Status
A32: =Partner_Rules!A5 -> House (Direct) | B32: =SUMIFS($H$8:$H$27,$D$8:$D$27,A32) -> 6647.61 | C32: =SUMIFS($J$8:$J$27,$D$8:$D$27,A32)-SUMIFS($K$8:$K$27,$D$8:$D$27,A32)+IFERROR(SUMIFS($K$8:$K$27,$D$8:$D$27,INDEX(Partner_Rules!$A$5:$A$9,MATCH(A32,Partner_Rules!$C$5:$C$9,0))),0) -> 0 | D32: =IF(B32=0,"",C32/B32) -> 0 | E32: 0 | F32: =C32-E32 -> 0 | G32: =IF(C32=0,"N/A",IF(F32<=0.005,"Paid",IF(E32=0,"Unpaid","Partial"))) -> N/A
A33: =Partner_Rules!A6 -> Partner Alpha | B33: =SUMIFS($H$8:$H$27,$D$8:$D$27,A33) -> 19151.1 | C33: =SUMIFS($J$8:$J$27,$D$8:$D$27,A33)-SUMIFS($K$8:$K$27,$D$8:$D$27,A33)+IFERROR(SUMIFS($K$8:$K$27,$D$8:$D$27,INDEX(Partner_Rules!$A$5:$A$9,MATCH(A33,Partner_Rules!$C$5:$C$9,0))),0) -> 7660.44 | D33: =IF(B33=0,"",C33/B33) -> 0.4 | E33: 7660.44 | F33: =C33-E33 -> 0 | G33: =IF(C33=0,"N/A",IF(F33<=0.005,"Paid",IF(E33=0,"Unpaid","Partial"))) -> Paid
A34: =Partner_Rules!A7 -> Partner Beta | B34: =SUMIFS($H$8:$H$27,$D$8:$D$27,A34) -> 19490.75 | C34: =SUMIFS($J$8:$J$27,$D$8:$D$27,A34)-SUMIFS($K$8:$K$27,$D$8:$D$27,A34)+IFERROR(SUMIFS($K$8:$K$27,$D$8:$D$27,INDEX(Partner_Rules!$A$5:$A$9,MATCH(A34,Partner_Rules!$C$5:$C$9,0))),0) -> 5164.9249 | D34: =IF(B34=0,"",C34/B34) -> 0.26499364 | E34: 2580 | F34: =C34-E34 -> 2584.9249 | G34: =IF(C34=0,"N/A",IF(F34<=0.005,"Paid",IF(E34=0,"Unpaid","Partial"))) -> Partial
A35: =Partner_Rules!A8 -> Partner Gamma | B35: =SUMIFS($H$8:$H$27,$D$8:$D$27,A35) -> 0 | C35: =SUMIFS($J$8:$J$27,$D$8:$D$27,A35)-SUMIFS($K$8:$K$27,$D$8:$D$27,A35)+IFERROR(SUMIFS($K$8:$K$27,$D$8:$D$27,INDEX(Partner_Rules!$A$5:$A$9,MATCH(A35,Partner_Rules!$C$5:$C$9,0))),0) -> 1721.6416 | D35: =IF(B35=0,"",C35/B35) | E35: 0 | F35: =C35-E35 -> 1721.6416 | G35: =IF(C35=0,"N/A",IF(F35<=0.005,"Paid",IF(E35=0,"Unpaid","Partial"))) -> Unpaid
A36: =Partner_Rules!A9 -> Partner Delta | B36: =SUMIFS($H$8:$H$27,$D$8:$D$27,A36) -> 15284.81 | C36: =SUMIFS($J$8:$J$27,$D$8:$D$27,A36)-SUMIFS($K$8:$K$27,$D$8:$D$27,A36)+IFERROR(SUMIFS($K$8:$K$27,$D$8:$D$27,INDEX(Partner_Rules!$A$5:$A$9,MATCH(A36,Partner_Rules!$C$5:$C$9,0))),0) -> 6454.061 | D36: =IF(B36=0,"",C36/B36) -> 0.42225327 | E36: 0 | F36: =C36-E36 -> 6454.061 | G36: =IF(C36=0,"N/A",IF(F36<=0.005,"Paid",IF(E36=0,"Unpaid","Partial"))) -> Unpaid
A37: TOTAL | B37: =SUM(B32:B36) -> 60574.27 | C37: =SUM(C32:C36) -> 21001.068 | D37: =IF(B37=0,"",C37/B37) -> 0.34669947 | E37: =SUM(E32:E36) -> 10240.44 | F37: =SUM(F32:F36) -> 10760.628 | H37: =IF(ABS(C37-J28)<0.01,"✓ Ties to calc","CHECK") -> ✓ Ties to calc
A38: Note: Beta payout is shown net of Gamma's split-of-split share; total partner cost is unchanged.

Sheet Reconciliation
A1: Residual Report-to-Bank Reconciliation
A2: ILLUSTRATIVE DATA ONLY — all processors, partners, merchants and figures are fictional.
A3: Reconciliation Month | B3: =Rev_Share_Calc!B3 -> 2026-09
A4: Preparer / Reviewer | B4: [Preparer] / [Reviewer]
A6: Source | B6: Expected per Report ($) | C6: Bank Deposit ($) | D6: Variance ($) | E6: Variance % | F6: Variance Category | G6: Explanation | H6: Owner | I6: Status | J6: Bank Ref / Date | L6: Category list
A7: Processor A | B7: =SUMIFS(Residual_Data!$F$5:$F$346,Residual_Data!$A$5:$A$346,$B$3,Residual_Data!$C$5:$C$346,A7) -> 10878.13 | C7: 10878.13 | D7: =C7-B7 -> 0 | E7: =IF(B7=0,"",D7/B7) -> 0 | F7: None | G7: Ties to report | H7: Finance Ops | I7: Closed | J7: Stmt 09/30 | L7: None
A8: Processor B | B8: =SUMIFS(Residual_Data!$F$5:$F$346,Residual_Data!$A$5:$A$346,$B$3,Residual_Data!$C$5:$C$346,A8) -> 14109.12 | C8: 14064.12 | D8: =C8-B8 -> -45 | E8: =IF(B8=0,"",D8/B8) -> -0.0031894264 | F8: Fees | G8: Monthly portal fee netted from deposit; book to expense. See missing-residual exception M-018 | H8: Finance Ops | I8: Closed | J8: Stmt 09/30 | L8: Timing
A9: Processor C | B9: =SUMIFS(Residual_Data!$F$5:$F$346,Residual_Data!$A$5:$A$346,$B$3,Residual_Data!$C$5:$C$346,A9) -> 10930.38 | C9: 10620.38 | D9: =C9-B9 -> -310 | E9: =IF(B9=0,"",D9/B9) -> -0.02836132 | F9: Processor Adjustment | G9: Prior-month chargeback residual clawback (M-011); support requested | H9: Finance Ops | I9: Open | J9: Stmt 09/30 | L9: Fees
A10: Processor D | B10: =SUMIFS(Residual_Data!$F$5:$F$346,Residual_Data!$A$5:$A$346,$B$3,Residual_Data!$C$5:$C$346,A10) -> 18333.39 | C10: 18333.39 | D10: =C10-B10 -> 0 | E10: =IF(B10=0,"",D10/B10) -> 0 | F10: None | G10: Ties to report | H10: Finance Ops | I10: Closed | J10: Stmt 09/30 | L10: Reserve Activity
A11: Gateway G | B11: =SUMIFS(Residual_Data!$F$5:$F$346,Residual_Data!$A$5:$A$346,$B$3,Residual_Data!$C$5:$C$346,A11) -> 6323.25 | C11: 0 | D11: =C11-B11 -> -6323.25 | E11: =IF(B11=0,"",D11/B11) -> -1 | F11: Timing | G11: Sep gateway fees deposited 10/02/2026; clears in Oct | H11: Finance Ops | I11: Closed | J11: Recv'd 10/02 | L11: Refunds
A12: TOTAL | B12: =SUM(B7:B11) -> 60574.27 | C12: =SUM(C7:C11) -> 53896.02 | D12: =SUM(D7:D11) -> -6678.25 | E12: =IF(B12=0,"",D12/B12) -> -0.11024896 | L12: Chargebacks
L13: ACH Rejects
A14: Control checks | L14: Processor Adjustment
A15: Variance with no category ($) | D15: =SUMPRODUCT((F7:F11="")*D7:D11) -> 0 | L15: Missing Data
A16: Timing items (clear next month) ($) | D16: =SUMIFS(D7:D11,F7:F11,"Timing") -> -6323.25 | L16: Duplicate Data
A17: Non-timing variance requiring action ($) | D17: =D12-D16 -> -355 | L17: True Error
A18: Open items (count) | D18: =COUNTIF(I7:I11,"Open") -> 1
A19: Rec status | D19: =IF(D15<>0,"UNEXPLAINED VARIANCE",IF(D18>0,"Explained — items open","Reconciled")) -> Explained — items open
A20: Report total ties to Rev_Share_Calc gross | D20: =IF(ABS(B12-Rev_Share_Calc!H28)<0.01,"✓ Ties","CHECK") -> ✓ Ties
A22: Missing / Zero Residual Exception Log (from Rev_Share_Calc flags)
A23: Merchant ID | B23: Source | C23: Prior Month Gross ($) | D23: Current Gross ($) | E23: At-Risk Revenue ($) | F23: Root Cause | G23: Action | H23: Owner | I23: Status | J23: Target Date
A24: M-005 | B24: =INDEX(Rev_Share_Calc!$C$8:$C$27,MATCH(A24,Rev_Share_Calc!$A$8:$A$27,0)) -> Processor A | C24: =INDEX(Rev_Share_Calc!$M$8:$M$27,MATCH(A24,Rev_Share_Calc!$A$8:$A$27,0)) -> 3173.64 | D24: =INDEX(Rev_Share_Calc!$H$8:$H$27,MATCH(A24,Rev_Share_Calc!$A$8:$A$27,0)) -> 0 | E24: =MAX(C24-D24,0) -> 3173.64 | F24: Merchant closure confirmed by processor (account closed 09/12) | G24: Remove from forecast; confirm final residual | H24: Finance Ops | I24: Closed | J24: —
A25: M-018 | B25: =INDEX(Rev_Share_Calc!$C$8:$C$27,MATCH(A25,Rev_Share_Calc!$A$8:$A$27,0)) -> Processor B | C25: =INDEX(Rev_Share_Calc!$M$8:$M$27,MATCH(A25,Rev_Share_Calc!$A$8:$A$27,0)) -> 2776.52 | D25: =INDEX(Rev_Share_Calc!$H$8:$H$27,MATCH(A25,Rev_Share_Calc!$A$8:$A$27,0)) -> 533.1 | E25: =MAX(C25-D25,0) -> 2243.42 | F25: Merchant processed volume but missing from processor residual report | G25: Escalate to processor rep; request corrected report | H25: Finance Ops | I25: Open | J25: 11/15/2026
A26: M-012 | B26: =INDEX(Rev_Share_Calc!$C$8:$C$27,MATCH(A26,Rev_Share_Calc!$A$8:$A$27,0)) -> Processor D | C26: =INDEX(Rev_Share_Calc!$M$8:$M$27,MATCH(A26,Rev_Share_Calc!$A$8:$A$27,0)) -> 8384.02 | D26: =INDEX(Rev_Share_Calc!$H$8:$H$27,MATCH(A26,Rev_Share_Calc!$A$8:$A$27,0)) -> 11966.52 | E26: =MAX(C26-D26,0) -> 0 | F26: New merchant ramp (onboarded Jul-26) — expected MoM increase | G26: No action; monitor ramp vs. forecast | H26: Finance Ops | I26: Closed | J26: —

Sheet Profitability
A1: Profitability — Trailing 12 Months (Oct-25 to Sep-26)
A2: ILLUSTRATIVE DATA ONLY — all processors, partners, merchants and figures are fictional.
A3: Gross residual is reported net of processor expense; no additional processing cost deducted. Operating cost allocation is out of scope, so Net Revenue ≠ true net profit.
A5: Source | B5: Volume ($) | C5: Gross Revenue ($) | D5: Residual Yield (bps) | E5: Partner Payout ($) | F5: Company Net Revenue ($) | G5: Net Retention % | H5: % of Total Net
A6: Processor A | B6: =SUMIFS(Residual_Data!$E$5:$E$346,Residual_Data!$C$5:$C$346,A6) -> 50608907 | C6: =SUMIFS(Residual_Data!$F$5:$F$346,Residual_Data!$C$5:$C$346,A6) -> 152337.79 | D6: =IF(B6=0,"n/a",C6/B6*10000) -> 30.100984 | E6: =SUMIFS(Residual_Data!$I$5:$I$346,Residual_Data!$C$5:$C$346,A6) -> 50581.478 | F6: =C6-E6 -> 101756.31 | G6: =IF(C6=0,"",F6/C6) -> 0.667965 | H6: =F6/$F$11 -> 0.24336247
A7: Processor B | B7: =SUMIFS(Residual_Data!$E$5:$E$346,Residual_Data!$C$5:$C$346,A7) -> 57462848 | C7: =SUMIFS(Residual_Data!$F$5:$F$346,Residual_Data!$C$5:$C$346,A7) -> 183651.06 | D7: =IF(B7=0,"n/a",C7/B7*10000) -> 31.959965 | E7: =SUMIFS(Residual_Data!$I$5:$I$346,Residual_Data!$C$5:$C$346,A7) -> 56684.2 | F7: =C7-E7 -> 126966.86 | G7: =IF(C7=0,"",F7/C7) -> 0.69134837 | H7: =F7/$F$11 -> 0.30365653
A8: Processor C | B8: =SUMIFS(Residual_Data!$E$5:$E$346,Residual_Data!$C$5:$C$346,A8) -> 29270656 | C8: =SUMIFS(Residual_Data!$F$5:$F$346,Residual_Data!$C$5:$C$346,A8) -> 123215.24 | D8: =IF(B8=0,"n/a",C8/B8*10000) -> 42.095141 | E8: =SUMIFS(Residual_Data!$I$5:$I$346,Residual_Data!$C$5:$C$346,A8) -> 44846.199 | F8: =C8-E8 -> 78369.041 | G8: =IF(C8=0,"",F8/C8) -> 0.63603367 | H8: =F8/$F$11 -> 0.18742899
A9: Processor D | B9: =SUMIFS(Residual_Data!$E$5:$E$346,Residual_Data!$C$5:$C$346,A9) -> 33272437 | C9: =SUMIFS(Residual_Data!$F$5:$F$346,Residual_Data!$C$5:$C$346,A9) -> 114143.82 | D9: =IF(B9=0,"n/a",C9/B9*10000) -> 34.305819 | E9: =SUMIFS(Residual_Data!$I$5:$I$346,Residual_Data!$C$5:$C$346,A9) -> 41640.168 | F9: =C9-E9 -> 72503.652 | G9: =IF(C9=0,"",F9/C9) -> 0.6351956 | H9: =F9/$F$11 -> 0.17340121
A10: Gateway G | B10: =SUMIFS(Residual_Data!$E$5:$E$346,Residual_Data!$C$5:$C$346,A10) -> 0 | C10: =SUMIFS(Residual_Data!$F$5:$F$346,Residual_Data!$C$5:$C$346,A10) -> 56148.7 | D10: =IF(B10=0,"n/a",C10/B10*10000) -> n/a | E10: =SUMIFS(Residual_Data!$I$5:$I$346,Residual_Data!$C$5:$C$346,A10) -> 17618.002 | F10: =C10-E10 -> 38530.698 | G10: =IF(C10=0,"",F10/C10) -> 0.68622599 | H10: =F10/$F$11 -> 0.0921508
A11: TOTAL | B11: =SUM(B6:B10) -> 170614848 | C11: =SUM(C6:C10) -> 629496.61 | D11: =SUMIFS(Residual_Data!$F$5:$F$346,Residual_Data!$D$5:$D$346,"Processing Residual")/B11*10000 -> 33.604807 | E11: =SUM(E6:E10) -> 211370.05 | F11: =SUM(F6:F10) -> 418126.56 | G11: =F11/C11 -> 0.66422369 | H11: =F11/$F$11 -> 1
A14: Partner | B14: Volume ($) | C14: Gross Revenue ($) | D14: Residual Yield (bps) | E14: Partner Payout ($) | F14: Company Net Revenue ($) | G14: Net Retention % | H14: % of Total Net
A15: House (Direct) | B15: =SUMIFS(Residual_Data!$E$5:$E$346,Residual_Data!$G$5:$G$346,A15) -> 30642451 | C15: =SUMIFS(Residual_Data!$F$5:$F$346,Residual_Data!$G$5:$G$346,A15) -> 98904.93 | D15: =IF(B15=0,"n/a",SUMIFS(Residual_Data!$F$5:$F$346,Residual_Data!$G$5:$G$346,A15,Residual_Data!$D$5:$D$346,"Processing Residual")/B15*10000) -> 29.321799 | E15: =SUMIFS(Residual_Data!$I$5:$I$346,Residual_Data!$G$5:$G$346,A15) -> 0 | F15: =C15-E15 -> 98904.93 | G15: =IF(C15=0,"",F15/C15) -> 1 | H15: =F15/$F$11 -> 0.23654304
A16: Partner Alpha | B16: =SUMIFS(Residual_Data!$E$5:$E$346,Residual_Data!$G$5:$G$346,A16) -> 68791971 | C16: =SUMIFS(Residual_Data!$F$5:$F$346,Residual_Data!$G$5:$G$346,A16) -> 250164.9 | D16: =IF(B16=0,"n/a",SUMIFS(Residual_Data!$F$5:$F$346,Residual_Data!$G$5:$G$346,A16,Residual_Data!$D$5:$D$346,"Processing Residual")/B16*10000) -> 32.910505 | E16: =SUMIFS(Residual_Data!$I$5:$I$346,Residual_Data!$G$5:$G$346,A16) -> 100065.96 | F16: =C16-E16 -> 150098.94 | G16: =IF(C16=0,"",F16/C16) -> 0.6 | H16: =F16/$F$11 -> 0.35897968
A17: Partner Beta | B17: =SUMIFS(Residual_Data!$E$5:$E$346,Residual_Data!$G$5:$G$346,A17) -> 31986893 | C17: =SUMIFS(Residual_Data!$F$5:$F$346,Residual_Data!$G$5:$G$346,A17) -> 107111.85 | D17: =IF(B17=0,"n/a",SUMIFS(Residual_Data!$F$5:$F$346,Residual_Data!$G$5:$G$346,A17,Residual_Data!$D$5:$D$346,"Processing Residual")/B17*10000) -> 30.570584 | E17: =SUMIFS(Residual_Data!$I$5:$I$346,Residual_Data!$G$5:$G$346,A17) -> 38184.675 | F17: =C17-E17 -> 68927.174 | G17: =IF(C17=0,"",F17/C17) -> 0.64350653 | H17: =F17/$F$11 -> 0.16484763
A18: Partner Delta | B18: =SUMIFS(Residual_Data!$E$5:$E$346,Residual_Data!$G$5:$G$346,A18) -> 39193533 | C18: =SUMIFS(Residual_Data!$F$5:$F$346,Residual_Data!$G$5:$G$346,A18) -> 173314.93 | D18: =IF(B18=0,"n/a",SUMIFS(Residual_Data!$F$5:$F$346,Residual_Data!$G$5:$G$346,A18,Residual_Data!$D$5:$D$346,"Processing Residual")/B18*10000) -> 40.648308 | E18: =SUMIFS(Residual_Data!$I$5:$I$346,Residual_Data!$G$5:$G$346,A18) -> 73119.411 | F18: =C18-E18 -> 100195.52 | G18: =IF(C18=0,"",F18/C18) -> 0.57811245 | H18: =F18/$F$11 -> 0.23962964
A19: Partner Beta payout includes Partner Gamma's split-of-split share (paid through Beta's agreement).
A21: Monthly Trend
A22: Month | B22: Volume ($) | C22: Gross Revenue ($) | D22: Residual Yield (bps) | E22: Partner Payout ($) | F22: Company Net Revenue ($) | G22: Net Retention % | H22: MoM Net Δ %
A23: 2025-10 | B23: =SUMIFS(Residual_Data!$E$5:$E$346,Residual_Data!$A$5:$A$346,A23) -> 13239609 | C23: =SUMIFS(Residual_Data!$F$5:$F$346,Residual_Data!$A$5:$A$346,A23) -> 48602.78 | D23: =SUMIFS(Residual_Data!$F$5:$F$346,Residual_Data!$A$5:$A$346,A23,Residual_Data!$D$5:$D$346,"Processing Residual")/B23*10000 -> 33.515061 | E23: =SUMIFS(Residual_Data!$I$5:$I$346,Residual_Data!$A$5:$A$346,A23) -> 16258.72 | F23: =C23-E23 -> 32344.059 | G23: =F23/C23 -> 0.66547756
A24: 2025-11 | B24: =SUMIFS(Residual_Data!$E$5:$E$346,Residual_Data!$A$5:$A$346,A24) -> 13083030 | C24: =SUMIFS(Residual_Data!$F$5:$F$346,Residual_Data!$A$5:$A$346,A24) -> 48254.97 | D24: =SUMIFS(Residual_Data!$F$5:$F$346,Residual_Data!$A$5:$A$346,A24,Residual_Data!$D$5:$D$346,"Processing Residual")/B24*10000 -> 33.663012 | E24: =SUMIFS(Residual_Data!$I$5:$I$346,Residual_Data!$A$5:$A$346,A24) -> 16175.98 | F24: =C24-E24 -> 32078.989 | G24: =F24/C24 -> 0.66478105 | H24: =F24/F23-1 -> -0.0081953225
A25: 2025-12 | B25: =SUMIFS(Residual_Data!$E$5:$E$346,Residual_Data!$A$5:$A$346,A25) -> 13221166 | C25: =SUMIFS(Residual_Data!$F$5:$F$346,Residual_Data!$A$5:$A$346,A25) -> 48387.25 | D25: =SUMIFS(Residual_Data!$F$5:$F$346,Residual_Data!$A$5:$A$346,A25,Residual_Data!$D$5:$D$346,"Processing Residual")/B25*10000 -> 33.434305 | E25: =SUMIFS(Residual_Data!$I$5:$I$346,Residual_Data!$A$5:$A$346,A25) -> 16076.85 | F25: =C25-E25 -> 32310.4 | G25: =F25/C25 -> 0.66774615 | H25: =F25/F24-1 -> 0.0072137715
A26: 2026-01 | B26: =SUMIFS(Residual_Data!$E$5:$E$346,Residual_Data!$A$5:$A$346,A26) -> 13306098 | C26: =SUMIFS(Residual_Data!$F$5:$F$346,Residual_Data!$A$5:$A$346,A26) -> 48926.43 | D26: =SUMIFS(Residual_Data!$F$5:$F$346,Residual_Data!$A$5:$A$346,A26,Residual_Data!$D$5:$D$346,"Processing Residual")/B26*10000 -> 33.638509 | E26: =SUMIFS(Residual_Data!$I$5:$I$346,Residual_Data!$A$5:$A$346,A26) -> 16373.933 | F26: =C26-E26 -> 32552.497 | G26: =F26/C26 -> 0.66533562 | H26: =F26/F25-1 -> 0.0074928351
A27: 2026-02 | B27: =SUMIFS(Residual_Data!$E$5:$E$346,Residual_Data!$A$5:$A$346,A27) -> 13434939 | C27: =SUMIFS(Residual_Data!$F$5:$F$346,Residual_Data!$A$5:$A$346,A27) -> 49392.41 | D27: =SUMIFS(Residual_Data!$F$5:$F$346,Residual_Data!$A$5:$A$346,A27,Residual_Data!$D$5:$D$346,"Processing Residual")/B27*10000 -> 33.583599 | E27: =SUMIFS(Residual_Data!$I$5:$I$346,Residual_Data!$A$5:$A$346,A27) -> 16447.73 | F27: =C27-E27 -> 32944.68 | G27: =F27/C27 -> 0.66699884 | H27: =F27/F26-1 -> 0.012047724
A28: 2026-03 | B28: =SUMIFS(Residual_Data!$E$5:$E$346,Residual_Data!$A$5:$A$346,A28) -> 13797434 | C28: =SUMIFS(Residual_Data!$F$5:$F$346,Residual_Data!$A$5:$A$346,A28) -> 50761.21 | D28: =SUMIFS(Residual_Data!$F$5:$F$346,Residual_Data!$A$5:$A$346,A28,Residual_Data!$D$5:$D$346,"Processing Residual")/B28*10000 -> 33.634957 | E28: =SUMIFS(Residual_Data!$I$5:$I$346,Residual_Data!$A$5:$A$346,A28) -> 16981.867 | F28: =C28-E28 -> 33779.344 | G28: =F28/C28 -> 0.66545584 | H28: =F28/F27-1 -> 0.025335305
A29: 2026-04 | B29: =SUMIFS(Residual_Data!$E$5:$E$346,Residual_Data!$A$5:$A$346,A29) -> 14031788 | C29: =SUMIFS(Residual_Data!$F$5:$F$346,Residual_Data!$A$5:$A$346,A29) -> 51509.44 | D29: =SUMIFS(Residual_Data!$F$5:$F$346,Residual_Data!$A$5:$A$346,A29,Residual_Data!$D$5:$D$346,"Processing Residual")/B29*10000 -> 33.549139 | E29: =SUMIFS(Residual_Data!$I$5:$I$346,Residual_Data!$A$5:$A$346,A29) -> 17228.362 | F29: =C29-E29 -> 34281.078 | G29: =F29/C29 -> 0.66553001 | H29: =F29/F28-1 -> 0.014853293
A30: 2026-05 | B30: =SUMIFS(Residual_Data!$E$5:$E$346,Residual_Data!$A$5:$A$346,A30) -> 14006688 | C30: =SUMIFS(Residual_Data!$F$5:$F$346,Residual_Data!$A$5:$A$346,A30) -> 51485.36 | D30: =SUMIFS(Residual_Data!$F$5:$F$346,Residual_Data!$A$5:$A$346,A30,Residual_Data!$D$5:$D$346,"Processing Residual")/B30*10000 -> 33.603169 | E30: =SUMIFS(Residual_Data!$I$5:$I$346,Residual_Data!$A$5:$A$346,A30) -> 17228.768 | F30: =C30-E30 -> 34256.592 | G30: =F30/C30 -> 0.66536569 | H30: =F30/F29-1 -> -0.00071427159
A31: 2026-06 | B31: =SUMIFS(Residual_Data!$E$5:$E$346,Residual_Data!$A$5:$A$346,A31) -> 14106683 | C31: =SUMIFS(Residual_Data!$F$5:$F$346,Residual_Data!$A$5:$A$346,A31) -> 51737.28 | D31: =SUMIFS(Residual_Data!$F$5:$F$346,Residual_Data!$A$5:$A$346,A31,Residual_Data!$D$5:$D$346,"Processing Residual")/B31*10000 -> 33.50641 | E31: =SUMIFS(Residual_Data!$I$5:$I$346,Residual_Data!$A$5:$A$346,A31) -> 17234.635 | F31: =C31-E31 -> 34502.645 | G31: =F31/C31 -> 0.66688171 | H31: =F31/F30-1 -> 0.0071826614
A32: 2026-07 | B32: =SUMIFS(Residual_Data!$E$5:$E$346,Residual_Data!$A$5:$A$346,A32) -> 15480214 | C32: =SUMIFS(Residual_Data!$F$5:$F$346,Residual_Data!$A$5:$A$346,A32) -> 57306.98 | D32: =SUMIFS(Residual_Data!$F$5:$F$346,Residual_Data!$A$5:$A$346,A32,Residual_Data!$D$5:$D$346,"Processing Residual")/B32*10000 -> 33.643902 | E32: =SUMIFS(Residual_Data!$I$5:$I$346,Residual_Data!$A$5:$A$346,A32) -> 19240.736 | F32: =C32-E32 -> 38066.243 | G32: =F32/C32 -> 0.66425143 | H32: =F32/F31-1 -> 0.10328478
A33: 2026-08 | B33: =SUMIFS(Residual_Data!$E$5:$E$346,Residual_Data!$A$5:$A$346,A33) -> 16734415 | C33: =SUMIFS(Residual_Data!$F$5:$F$346,Residual_Data!$A$5:$A$346,A33) -> 62558.23 | D33: =SUMIFS(Residual_Data!$F$5:$F$346,Residual_Data!$A$5:$A$346,A33,Residual_Data!$D$5:$D$346,"Processing Residual")/B33*10000 -> 33.883366 | E33: =SUMIFS(Residual_Data!$I$5:$I$346,Residual_Data!$A$5:$A$346,A33) -> 21121.397 | F33: =C33-E33 -> 41436.833 | G33: =F33/C33 -> 0.66237221 | H33: =F33/F32-1 -> 0.088545367
A34: 2026-09 | B34: =SUMIFS(Residual_Data!$E$5:$E$346,Residual_Data!$A$5:$A$346,A34) -> 16172784 | C34: =SUMIFS(Residual_Data!$F$5:$F$346,Residual_Data!$A$5:$A$346,A34) -> 60574.27 | D34: =SUMIFS(Residual_Data!$F$5:$F$346,Residual_Data!$A$5:$A$346,A34,Residual_Data!$D$5:$D$346,"Processing Residual")/B34*10000 -> 33.544639 | E34: =SUMIFS(Residual_Data!$I$5:$I$346,Residual_Data!$A$5:$A$346,A34) -> 21001.068 | F34: =C34-E34 -> 39573.202 | G34: =F34/C34 -> 0.65330053 | H34: =F34/F33-1 -> -0.044975216
A35: Check: TTM total ties to monthly trend | C35: =IF(ABS(SUM(C23:C34)-C11)<0.01,"✓ Ties","CHECK") -> ✓ Ties

Sheet Forecast
A1: 12-Month Residual & Payout Forecast (Oct-26 to Sep-27)
A2: ILLUSTRATIVE DATA ONLY — all processors, partners, merchants and figures are fictional.
A4: Scenario (1=Downside, 2=Base, 3=Upside) | D4: 2
A5: Active scenario | D5: =CHOOSE(D4,"Downside","Base","Upside") -> Base
A7: Assumption | D7: Downside | E7: Base | F7: Upside | G7: Active | H7: Source / Rationale
A8: Monthly volume growth % | D8: 0 | E8: 0.012 | F8: 0.025 | G8: =CHOOSE($D$4,D8,E8,F8) -> 0.012 | H8: Base = TTM avg organic growth (illustrative)
A9: Monthly volume attrition % | D9: 0.02 | E9: 0.01 | F9: 0.005 | G9: =CHOOSE($D$4,D9,E9,F9) -> 0.01 | H9: Merchant closures / churn; Sep-26 closure (M-005) informs downside
A10: Monthly gateway fee growth % | D10: 0 | E10: 0.01 | F10: 0.02 | G10: =CHOOSE($D$4,D10,E10,F10) -> 0.01 | H10: Tracks gateway transaction count
A11: Starting volume (Sep-26 actual) | G11: =Rev_Share_Calc!E28 -> 16172784 | H11: Link: Rev_Share_Calc total
A12: Residual yield (bps, TTM blended) | G12: =Profitability!D11 -> 33.604807 | H12: Link: Profitability TTM yield
A13: Starting gateway fees (Sep-26 actual) | G13: =Rev_Share_Calc!G28 -> 6323.25 | H13: Link: Rev_Share_Calc
A14: Blended partner payout % (TTM) | G14: =Profitability!E11/Profitability!C11 -> 0.33577631 | H14: Link: TTM payout ÷ gross; assumes stable partner mix
A15: Recovery of missing residual (M-018) in Oct-26 ($) | G15: =Reconciliation!E25 -> 2243.42 | H15: One-time; assumes processor issues corrected report
A17: Line item | B17: 2026-10 | C17: 2026-11 | D17: 2026-12 | E17: 2027-01 | F17: 2027-02 | G17: 2027-03 | H17: 2027-04 | I17: 2027-05 | J17: 2027-06 | K17: 2027-07 | L17: 2027-08 | M17: 2027-09 | N17: FY Total
A18: Processing Volume ($) | B18: =$G$11*(1+$G$8)*(1-$G$9) -> 16203189 | C18: =B18*(1+$G$8)*(1-$G$9) -> 16233651 | D18: =C18*(1+$G$8)*(1-$G$9) -> 16264170 | E18: =D18*(1+$G$8)*(1-$G$9) -> 16294747 | F18: =E18*(1+$G$8)*(1-$G$9) -> 16325381 | G18: =F18*(1+$G$8)*(1-$G$9) -> 16356073 | H18: =G18*(1+$G$8)*(1-$G$9) -> 16386822 | I18: =H18*(1+$G$8)*(1-$G$9) -> 16417629 | J18: =I18*(1+$G$8)*(1-$G$9) -> 16448494 | ... M18: =L18*(1+$G$8)*(1-$G$9) -> 16541438 | N18: =SUM(B18:M18) -> 1.9646141e+08
A19: Processing Residual ($) | B19: =B18*$G$12/10000 -> 54450.504 | C19: =C18*$G$12/10000 -> 54552.871 | D19: =D18*$G$12/10000 -> 54655.43 | E19: =E18*$G$12/10000 -> 54758.182 | F19: =F18*$G$12/10000 -> 54861.128 | G19: =G18*$G$12/10000 -> 54964.267 | H19: =H18*$G$12/10000 -> 55067.6 | I19: =I18*$G$12/10000 -> 55171.127 | ... M19: =M18*$G$12/10000 -> 55587.185 | N19: =SUM(B19:M19) -> 660204.78
A20: Gateway Fees ($) | B20: =$G$13*(1+$G$10) -> 6386.4825 | C20: =B20*(1+$G$10) -> 6450.3473 | D20: =C20*(1+$G$10) -> 6514.8508 | E20: =D20*(1+$G$10) -> 6579.9993 | F20: =E20*(1+$G$10) -> 6645.7993 | G20: =F20*(1+$G$10) -> 6712.2573 | H20: =G20*(1+$G$10) -> 6779.3799 | I20: =H20*(1+$G$10) -> 6847.1737 | J20: =I20*(1+$G$10) -> 6915.6454 | ... M20: =L20*(1+$G$10) -> 7125.1964 | N20: =SUM(B20:M20) -> 80996.584
A21: One-time Recovery ($) | B21: =$G$15 -> 2243.42 | C21: 0 | D21: 0 | E21: 0 | F21: 0 | G21: 0 | H21: 0 | I21: 0 | J21: 0 | K21: 0 | L21: 0 | M21: 0 | N21: =SUM(B21:M21) -> 2243.42
A22: Gross Revenue ($) | B22: =SUM(B19:B21) -> 63080.406 | C22: =SUM(C19:C21) -> 61003.218 | D22: =SUM(D19:D21) -> 61170.281 | E22: =SUM(E19:E21) -> 61338.182 | F22: =SUM(F19:F21) -> 61506.927 | G22: =SUM(G19:G21) -> 61676.524 | H22: =SUM(H19:H21) -> 61846.979 | I22: =SUM(I19:I21) -> 62018.3 | ... M22: =SUM(M19:M21) -> 62712.381 | N22: =SUM(B22:M22) -> 743444.79
A23: Partner Payout ($) | B23: =B22*$G$14 -> 21180.906 | C23: =C22*$G$14 -> 20483.435 | D23: =D22*$G$14 -> 20539.531 | E23: =E22*$G$14 -> 20595.908 | F23: =F22*$G$14 -> 20652.569 | G23: =G22*$G$14 -> 20709.515 | H23: =H22*$G$14 -> 20766.75 | I23: =I22*$G$14 -> 20824.276 | ... M23: =M22*$G$14 -> 21057.332 | N23: =SUM(B23:M23) -> 249631.14
A24: Company Net Revenue ($) | B24: =B22-B23 -> 41899.501 | C24: =C22-C23 -> 40519.783 | D24: =D22-D23 -> 40630.75 | E24: =E22-E23 -> 40742.274 | F24: =F22-F23 -> 40854.358 | G24: =G22-G23 -> 40967.009 | H24: =H22-H23 -> 41080.229 | I24: =I22-I23 -> 41194.025 | ... M24: =M22-M23 -> 41655.05 | N24: =SUM(B24:M24) -> 493813.64
A26: vs. TTM actual net revenue | N26: =N24/Profitability!F11-1 -> 0.18101476
A27: Risks: partner mix shift changes payout %; processor pricing changes move yield; forecast excludes new partner signings and operating costs.

Sheet Portal_Audit
A1: Processor & Gateway Portal Audit Matrix
A2: ILLUSTRATIVE DATA ONLY — all processors, partners, merchants and figures are fictional. Template: rows 5–8 are examples; add one row per portal.
A4: Portal / Company | B4: Relationship Type | C4: Purpose | D4: Residual Report | E4: Merchant Statements | F4: Volume Detail | G4: Fees | H4: Funding / Deposits | I4: Reserves | J4: Chargebacks | K4: MID-Level Detail | L4: History Depth | M4: Export Formats | N4: Scheduled Reports | O4: API / Data Feed | P4: Best Source-of-Truth Report | Q4: Automation Potential | R4: 2FA Required | S4: 2FA Destination | T4: User Model | U4: Company-Controlled MFA | V4: Offboarding Process Documented | W4: Gaps / Actions
A5: Processor A | B5: Direct ISO | C5: Residuals, statements | D5: Y | E5: Y | F5: Y | G5: Y | H5: Y | I5: Y | J5: Y | K5: Y | L5: 24 mo | M5: CSV, PDF | N5: Y | O5: N | P5: Monthly Residual Detail (CSV) | Q5: High | R5: Y | S5: Shared mailbox | T5: Individual | U5: Y | V5: Y | W5: None
A6: Processor B | B6: Agency → ISO | C6: Residuals only | D6: Y | E6: N | F6: Y | G6: N | H6: N | I6: N | J6: N | K6: Y | L6: 12 mo | M6: XLSX | N6: N | O6: N | P6: Residual Summary (XLSX) | Q6: Medium | R6: Y | S6: Personal mobile | T6: Shared login | U6: N | V6: N | W6: Move 2FA to company device; request individual users
A7: Processor C | B7: Split-of-split | C7: Residuals, chargebacks | D7: Y | E7: Y | F7: Y | G7: Y | H7: Y | I7: Y | J7: Y | K7: Y | L7: 36 mo | M7: CSV, API | N7: Y | O7: Y | P7: API residual endpoint | Q7: High | R7: Y | S7: Authenticator app | T7: Individual | U7: Y | V7: Y | W7: Build API pull (Phase 2)
A8: Gateway G | B8: Gateway reseller | C8: Gateway billing, merchant config | D8: N | E8: N | F8: Y | G8: Y | H8: N | I8: N | J8: N | K8: Y | L8: 18 mo | M8: CSV | N8: N | O8: Y | P8: Merchant Billing Export | Q8: Medium | R8: N | S8: — | T8: Shared login | U8: N | V8: N | W8: Enable 2FA; document offboarding
A32: Governance summary
A33: Portals audited | C33: =COUNTA(A5:A30) -> 4
A34: Shared logins | C34: =COUNTIF(T5:T30,"Shared login") -> 2
A35: No 2FA | C35: =COUNTIF(R5:R30,"N") -> 1
A36: No documented offboarding | C36: =COUNTIF(V5:V30,"N") -> 2
A37: API / data feed available | C37: =COUNTIF(O5:O30,"Y") -> 2
